{
  "$schema": "https://developer.microsoft.com/json-schemas/fabric/item/report/definition/visualContainerMobileState/2.2.0/schema.json",
  "position": {
    "x": 0,
    "y": 3088,
    "z": 15000,
    "height": 35,
    "width": 90,
    "tabOrder": 9000
  },
  "objects": {
    "categoryLabels": [],
    "labels": [
      {
        "properties": {
          "fontSize": {
            "expr": {
              "Literal": {
                "Value": "8D"
              }
            }
          }
        }
      }
    ]
  }
}